manyapi/__init__.py
manyapi/anonfiles.py
manyapi/discord.py
manyapi/randomword.py
manyapi/youtube.py
manyapi-1.0.dist-info/LICENSE
manyapi-1.0.dist-info/METADATA
manyapi-1.0.dist-info/WHEEL
manyapi-1.0.dist-info/top_level.txt
manyapi-1.0.dist-info/RECORD
